{
  "name": "Natrilix 2.5mg 2.5 mg tablet",
  "generic": "Indapamide (2.5 mg)",
  "brand": "Servier",
  "images": [
    "https://product.dawaai.pk/800/sernat630_1671273840_1.webp",
    "https://product.dawaai.pk/800/sernat630_1671273840_1.png",
    "https://product.dawaai.pk/800/sernat630_1671273840_1.jpg"
  ],
  "labels": [
    "Hypertension",
    "Diuretic"
  ],
  "description": "",
  "link": "https://dawaai.pk/medicine/Natrilix-Tablet25-630.html",
  "version": "1.0.0",
  "label": "medicine"
}