{
  "name": "Fusil - HC  cream",
  "generic": "Hydrocortisone and Fusidic Acid, topical",
  "brand": "Tabroos",
  "images": [
    "https://product.dawaai.pk/800/tabfus38060_1628672760_3.webp",
    "https://product.dawaai.pk/800/tabfus38060_1628672760_3.png",
    "https://product.dawaai.pk/800/tabfus38060_1628672760_3.jpg"
  ],
  "labels": [
    "Corticosteroid Combinations, Topical"
  ],
  "description": "",
  "link": "https://dawaai.pk/medicine/fusil-hc-38060.html",
  "version": "1.0.0",
  "label": "medicine"
}