{
  "name": "Pentasa 500mg tablet",
  "generic": "Mesalazine (500mg)",
  "brand": "Atco",
  "images": [
    "https://product.dawaai.pk/800/atcpen1331_1642770373_2.webp",
    "https://product.dawaai.pk/800/atcpen1331_1642770373_2.png",
    "https://product.dawaai.pk/800/atcpen1331_1642770373_2.jpg"
  ],
  "labels": [
    "Intestinal inflammation",
    "Other Alimentary Tract Preps"
  ],
  "description": "",
  "link": "https://dawaai.pk/medicine/pentasa-50mg-1331.html",
  "version": "1.0.0",
  "label": "medicine"
}