{
  "name": "Ticovate  ointment",
  "generic": "Fluticasone Propionate",
  "brand": "Saffron",
  "images": [
    "https://product.dawaai.pk/800/saftic47610_1638963304_1.webp",
    "https://product.dawaai.pk/800/saftic47610_1638963304_1.png",
    "https://product.dawaai.pk/800/saftic47610_1638963304_1.jpg"
  ],
  "labels": [
    "Rhinitis",
    "Hay fever",
    "Corticosteroid, Plain"
  ],
  "description": "",
  "link": "https://dawaai.pk/medicine/ticovateointment10-gm-pack-47610.html",
  "version": "1.0.0",
  "label": "medicine"
}