{
  "name": "Betaderm-NM 10gm  cream",
  "generic": "Betamethasone",
  "brand": "Atco",
  "images": [
    "https://product.dawaai.pk/800/atcbet37523_1628672262_3.webp",
    "https://product.dawaai.pk/800/atcbet37523_1628672262_3.png",
    "https://product.dawaai.pk/800/atcbet37523_1628672262_3.jpg"
  ],
  "labels": [
    "Asthma",
    "Allergy",
    "Rheumatoid arthritis",
    "Corticosteroid Combinations, Topical"
  ],
  "description": "Betamethasone belongs to a group of medicines known as corticosteroids. It works by activating natural substances in the skin to reduce swelling, redness, and itching. Betamethasone is used to treat itching, redness, dryness, scaling, inflammation, and discomfort associated with a variety of skin conditions like psoriasis and eczema. It can also be used to treat rheumatoid arthritis, systemic lupus erythematosus, angioedema, asthma, Crohn’s disease, and dermatitis.",
  "link": "https://dawaai.pk/medicine/betaderm-nm-10gm-37523.html",
  "version": "1.0.0",
  "label": "medicine"
}