{
  "name": "Funge 250mg  tablet",
  "generic": "Terbinafine",
  "brand": "Wilshire",
  "images": [
    "https://product.dawaai.pk/800/fun1530_1.webp",
    "https://product.dawaai.pk/800/fun1530_1.png",
    "https://product.dawaai.pk/800/fun1530_1.jpg"
  ],
  "labels": [
    "Fungal infections",
    "Antifungal, Systemic"
  ],
  "description": "Terbinafine is used to treat certain types of fungal infections (for example, of the fingernail or toenail). Terbinafine works by stopping the growth of fungus. Terbinafine belongs to a class of medicines known as antifungals.",
  "link": "https://dawaai.pk/medicine/funge-250mg-1530.html",
  "version": "1.0.0",
  "label": "medicine"
}