{
  "name": "Sulphakream-N 80gm cream",
  "generic": "Sulphanilamide (80gm)",
  "brand": "Well.pk",
  "images": [
    "https://product.dawaai.pk/800/dawsul12875_1627278532_1.webp",
    "https://product.dawaai.pk/800/dawsul12875_1627278532_1.png",
    "https://product.dawaai.pk/800/dawsul12875_1627278532_1.jpg"
  ],
  "labels": [
    "Bacterial infections",
    "Gynaecological Anti-Infective"
  ],
  "description": "",
  "link": "https://dawaai.pk/medicine/sulphakream-n-12875.html",
  "version": "1.0.0",
  "label": "medicine"
}