{
  "name": "Maladar 500mg/25mg suspension",
  "generic": "Sulfadoxine (500mg)Pyrimethamine (25mg)",
  "brand": "Efroze",
  "images": [
    "https://product.dawaai.pk/800/efrmal18140_1634389914_3.webp",
    "https://product.dawaai.pk/800/efrmal18140_1634389914_3.png",
    "https://product.dawaai.pk/800/efrmal18140_1634389914_3.jpg"
  ],
  "labels": [
    "Malaria",
    "Antimalarial"
  ],
  "description": "",
  "link": "https://dawaai.pk/medicine/maladar-18140.html",
  "version": "1.0.0",
  "label": "medicine"
}