{
  "name": "Topmate 50mg tablet",
  "generic": "Topiramate (50mg)",
  "brand": "Maple",
  "images": [
    "https://product.dawaai.pk/800/soutop7793_1.webp",
    "https://product.dawaai.pk/800/soutop7793_1.png",
    "https://product.dawaai.pk/800/soutop7793_1.jpg"
  ],
  "labels": [
    "Seizure",
    "Anti-epileptic"
  ],
  "description": "Topiramate is a medicine that is used to treat seizures, which are sudden, uncontrollable electrical abnormalities in the brain that cause aberrant behavior and unconsciousness.  Topiramate  is also used for preventing migraine. Topiramate acts by lowering aberrant electrical activity in the brain.",
  "link": "https://dawaai.pk/medicine/topmate-50mg-tablet-7793.html",
  "version": "1.0.0",
  "label": "medicine"
}