{
  "name": "Lucast 5mg tablet",
  "generic": "Montelukast (5mg)",
  "brand": "AGP",
  "images": [
    "https://product.dawaai.pk/800/agpluc42846_1654756941_1.webp",
    "https://product.dawaai.pk/800/agpluc42846_1654756941_1.png",
    "https://product.dawaai.pk/800/agpluc42846_1654756941_1.jpg"
  ],
  "labels": [
    "Asthma",
    "Bronchodilator and Anti-asthma Preps: Orals/Parenterals"
  ],
  "description": "",
  "link": "https://dawaai.pk/medicine/lucast-4-42846.html",
  "version": "1.0.0",
  "label": "medicine"
}