{
  "name": "Trikat MR 35 mg tablet",
  "generic": "Trimetazidine dihydrochloride (35 mg)",
  "brand": "Next Pharmaceutical",
  "images": [
    "https://product.dawaai.pk/800/nex46922_1632306645_3.webp",
    "https://product.dawaai.pk/800/nex46922_1632306645_3.png",
    "https://product.dawaai.pk/800/nex46922_1632306645_3.jpg"
  ],
  "labels": [
    "Prevents angina",
    "Cardiac Therapy"
  ],
  "description": "",
  "link": "https://dawaai.pk/medicine/trikat-mr-40139.html",
  "version": "1.0.0",
  "label": "medicine"
}