{
  "name": "Poze 15 mg tablet",
  "generic": "Pioglitazone (15 mg)",
  "brand": "AGP",
  "images": [
    "https://product.dawaai.pk/800/agppoz11428_1654776621_1.webp",
    "https://product.dawaai.pk/800/agppoz11428_1654776621_1.png",
    "https://product.dawaai.pk/800/agppoz11428_1654776621_1.jpg"
  ],
  "labels": [
    "Type 2 diabetes",
    "Hypoglycaemic excluding Insulin"
  ],
  "description": "",
  "link": "https://dawaai.pk/medicine/poze-11428.html",
  "version": "1.0.0",
  "label": "medicine"
}