{
  "name": "Neomercazole 5mg tablet",
  "generic": "Carbimazole (5mg)",
  "brand": "Ray Pharma",
  "images": [
    "https://product.dawaai.pk/800/rayneo209_1663153008_2.webp",
    "https://product.dawaai.pk/800/rayneo209_1663153008_2.png",
    "https://product.dawaai.pk/800/rayneo209_1663153008_2.jpg"
  ],
  "labels": [
    "Hyperthyroidism",
    "Thyroid Therapy"
  ],
  "description": "",
  "link": "https://dawaai.pk/medicine/Neomercazoletab-Tablet5-209.html",
  "version": "1.0.0",
  "label": "medicine"
}