{
  "name": "Myrin 300mg/ 75mg/ 150mg tablet",
  "generic": "Ethambutol (300mg)INH ( 75mg)Rifampicin ( 150mg)",
  "brand": "Wyeth",
  "images": [
    "https://product.dawaai.pk/800/wyemyr243_2.webp",
    "https://product.dawaai.pk/800/wyemyr243_2.png",
    "https://product.dawaai.pk/800/wyemyr243_2.jpg"
  ],
  "labels": [
    "Tuberculosis",
    "Antituberculosis, Preps"
  ],
  "description": "",
  "link": "https://dawaai.pk/medicine/MYRIN-Tablet300mg-243.html",
  "version": "1.0.0",
  "label": "medicine"
}