{
  "name": "Resque 200 mg / 5 ml dry powder suspension",
  "generic": "Azithromycin (200 mg )",
  "brand": "Stand Pharm",
  "images": [],
  "labels": [
    "Bacterial infections",
    "Antibacterial"
  ],
  "description": "Azithromycin is a broad-spectrum medicine that stops the growth of bacteria causing infections. It gets inside the infected tissue where it is relieved slowly over time, fighting bacteria for a long period. It is used to treat the following conditions:",
  "link": "https://dawaai.pk/medicine/resque-200-mg-5-ml-dry-powder-suspension-30-ml-bottle-47863.html",
  "version": "1.0.0",
  "label": "medicine"
}