{
  "name": "Norditropin nordilet 5mg/1.5ml injection",
  "generic": "Somatropin (5mg)",
  "brand": "Novo Nordisk",
  "images": [
    "https://product.dawaai.pk/800/novnor22614_1.webp",
    "https://product.dawaai.pk/800/novnor22614_1.png",
    "https://product.dawaai.pk/800/novnor22614_1.jpg"
  ],
  "labels": [
    "Growth hormone deficiency",
    "Growth Hormones"
  ],
  "description": "",
  "link": "https://dawaai.pk/medicine/norditropin-nordilet-22614.html",
  "version": "1.0.0",
  "label": "medicine"
}