{
  "name": "Tamsolin 0.4 mg capsule",
  "generic": "Tamsulosin HCl (0.4 mg)",
  "brand": "Getz Pharma",
  "images": [
    "https://product.dawaai.pk/800/tam1719_1655732638_2.webp",
    "https://product.dawaai.pk/800/tam1719_1655732638_2.png",
    "https://product.dawaai.pk/800/tam1719_1655732638_2.jpg"
  ],
  "labels": [
    "Enlarged prostate glands",
    "BPH & Drugs for Urinary Retention"
  ],
  "description": "Tamsulosin HCL is used by men for the treatment of the symptoms of an enlarged prostate. It does not shrink the prostate but actually works by relaxing the muscles in the prostate and the bladder. It belongs to a group of medicines called alpha blockers.",
  "link": "https://dawaai.pk/medicine/tamsolin-04mg-1719.html",
  "version": "1.0.0",
  "label": "medicine"
}