{
  "name": "Genurin Semplice 200mg  tablet",
  "generic": "Flavoxate",
  "brand": "Pacific Pharma",
  "images": [
    "https://product.dawaai.pk/800/gen1661_1671866739_1.webp",
    "https://product.dawaai.pk/800/gen1661_1671866739_1.png",
    "https://product.dawaai.pk/800/gen1661_1671866739_1.jpg"
  ],
  "labels": [
    "Dysuria",
    "Urinary Incontinence Products"
  ],
  "description": "",
  "link": "https://dawaai.pk/medicine/genurin-semplica-200mg-1661.html",
  "version": "1.0.0",
  "label": "medicine"
}