{
  "name": "Oxivant 500 mg / 100 mg tablets",
  "generic": "Supplements (500 mg )Vitamins ( 100 mg)",
  "brand": "Avant",
  "images": [],
  "labels": [
    "Nutritional deficiencies",
    "Other Vitamins"
  ],
  "description": "Supplements contain several vitamins and minerals. It is indicated for promoting growth in children, stronger muscles and bone tissues, weight gain, fatigue of any nature, anorexia and malnutrition, general weakness, decreased alertness, and convalescence. Multivitamins and minerals are used to supplement nutrients that are not obtained from food. Multivitamins and minerals also treat vitamin and mineral imbalances caused by disease, pregnancy, poor diet, digestive problems, certain medicines, and a number of other conditions.",
  "link": "https://dawaai.pk/medicine/oxivant-500-mg-100-mg-tablets-2-x-10s-pack-48081.html",
  "version": "1.0.0",
  "label": "medicine"
}