{
  "name": "Myteka 4mg tablet",
  "generic": "Montelukast (4mg)",
  "brand": "Hilton",
  "images": [
    "https://product.dawaai.pk/800/hilmyt631_1659513130_3.webp",
    "https://product.dawaai.pk/800/hilmyt631_1659513130_3.png",
    "https://product.dawaai.pk/800/hilmyt631_1659513130_3.jpg"
  ],
  "labels": [
    "Asthma",
    "Bronchodilator and Anti-asthma Preps: Orals/Parenterals"
  ],
  "description": "Myteka 4mg tablet is a medication produced by Hilton that contains the active ingredient Montelukast. It belongs to a class of drugs known as leukotriene receptor antagonists, which work by blocking the action of certain natural substances in the body that cause inflammation. This medication is available in the form of oral tablets and is used to prevent and treat asthma symptoms, seasonal allergies, and exercise-induced bronchoconstriction.",
  "link": "https://dawaai.pk/medicine/Mytekatab-Tablet10-631.html",
  "version": "1.0.0",
  "label": "medicine"
}