{
  "name": "Ofylin 40mg tablet",
  "generic": "Doxofylline (40mg)",
  "brand": "Continental Pharma",
  "images": [],
  "labels": [
    "Asthma",
    "Bronchodilator and Anti-asthma Preps: Orals/Parenterals"
  ],
  "description": "Doxofylline is used to asthma, a breathing disorder, and its associated symptoms, such as shortness of breath and wheezing. It is effective in most patients with asthma, contains Doxofylline as its active component, and helps control the severity of symptoms occurring in asthma.",
  "link": "https://dawaai.pk/medicine/ofylin-1-42744.html",
  "version": "1.0.0",
  "label": "medicine"
}